passkeys/.DS_Store
passkeys/__init__.py
passkeys/admin.py
passkeys/apps.py
passkeys/backend.py
passkeys/management/__init__.py
passkeys/management/commands/__init__.py
passkeys/management/commands/reset_passkeys.py
passkeys/migrations/0001_initial.py
passkeys/migrations/__init__.py
passkeys/models.py
passkeys/static/passkeys/.DS_Store
passkeys/static/passkeys/passkeys.js
passkeys/templates/admin/base.html
passkeys/templates/admin/login.html
passkeys/urls.py
passkeys/utils.py
passkeys/views.py
django_passkey_auth-0.2.0.dist-info/WHEEL
django_passkey_auth-0.2.0.dist-info/METADATA
django_passkey_auth-0.2.0.dist-info/RECORD
