Metadata-Version: 2.3
Name: django-passkey-auth
Version: 0.2.0
Summary: Passkey authentication for Django
Author: Dan Watson
Author-email: Dan Watson <dcwatson@gmail.com>
License: MIT License
Classifier: Framework :: Django
Classifier: Programming Language :: Python :: 3
Classifier: Development Status :: 3 - Alpha
Requires-Dist: django>=4.2
Requires-Dist: fido2
Requires-Python: >=3.10
Project-URL: Repository, https://github.com/dcwatson/django-passkey-auth
